odoo/addons/support_branding/README.rst
odoo/addons/support_branding/__init__.py
odoo/addons/support_branding/__manifest__.py
odoo/addons/support_branding/demo/ir_config_parameter_data.xml
odoo/addons/support_branding/i18n/it.po
odoo/addons/support_branding/i18n/nl.po
odoo/addons/support_branding/i18n/sl.po
odoo/addons/support_branding/i18n/support_branding.pot
odoo/addons/support_branding/models/__init__.py
odoo/addons/support_branding/models/res_company.py
odoo/addons/support_branding/models/res_config_settings.py
odoo/addons/support_branding/readme/CONTRIBUTORS.rst
odoo/addons/support_branding/readme/DESCRIPTION.rst
odoo/addons/support_branding/static/description/icon.png
odoo/addons/support_branding/static/description/index.html
odoo/addons/support_branding/static/src/css/support_branding.css
odoo/addons/support_branding/static/src/js/res_config_edition.js
odoo/addons/support_branding/static/src/js/support_branding.js
odoo/addons/support_branding/static/src/js/user_menu.js
odoo/addons/support_branding/static/src/tests/support_branding_tests.js
odoo/addons/support_branding/static/src/xml/base.xml
odoo/addons/support_branding/tests/__init__.py
odoo/addons/support_branding/tests/test_support_branding.py
odoo/addons/support_branding/views/asset.xml
odoo/addons/support_branding/views/res_config_settings.xml
odoo14_addon_support_branding-14.0.1.2.0.dist-info/METADATA
odoo14_addon_support_branding-14.0.1.2.0.dist-info/WHEEL
odoo14_addon_support_branding-14.0.1.2.0.dist-info/top_level.txt
odoo14_addon_support_branding-14.0.1.2.0.dist-info/RECORD
